sticklight/__init__.py
sticklight/_post_event.py
sticklight/auth.py
sticklight/capture.py
sticklight/consts.py
sticklight/context.py
sticklight/errors.py
sticklight/init.py
sticklight/py.typed
sticklight-0.1.7.dist-info/METADATA
sticklight-0.1.7.dist-info/WHEEL
sticklight-0.1.7.dist-info/licenses/LICENSE
sticklight-0.1.7.dist-info/RECORD
