Metadata-Version: 2.4
Name: sticklight
Version: 0.1.7
Summary: The Official Sticklight Python SDK
Project-URL: Homepage, https://sticklight.io
Project-URL: Issues, https://github.com/sticklight/sticklight-python/issues
Project-URL: Repository, https://github.com/sticklight/sticklight-python
Project-URL: Documentation, https://docs.sticklight.io
Project-URL: Changelog, https://github.com/sticklight/sticklight-python/blob/main/CHANGELOG.md
License-File: LICENSE
Keywords: agent,ai,analytics,anthropic,chatbot,customer support,data,data-driven,gpt,insights,llm,logging,metrics,observability,openai,platform,product,product analytics,sticklight,support
Classifier: Development Status :: 4 - Beta
Classifier: Intended Audience :: Developers
Classifier: License :: OSI Approved :: Apache Software License
Classifier: Programming Language :: Python :: 3.10
Classifier: Programming Language :: Python :: 3.11
Classifier: Programming Language :: Python :: 3.12
Requires-Python: >=3.10
Requires-Dist: aiohttp[speedups]>=3.11.12
Requires-Dist: requests>=2.32.3
